{"nm":"main","ddd":0,"h":500,"w":500,"meta":{"g":"@lottiefiles/toolkit-js 0.33.2"},"layers":[{"ty":0,"nm":"Bluetooth","sr":1,"st":0,"op":34,"ip":0,"hd":false,"ddd":0,"bm":0,"hasMask":false,"ao":0,"ks":{"a":{"a":0,"k":[250,250,0],"ix":1},"s":{"a":0,"k":[100,100,100],"ix":6},"sk":{"a":0,"k":0},"p":{"a":0,"k":[250,250,0],"ix":2},"r":{"a":0,"k":0,"ix":10},"sa":{"a":0,"k":0},"o":{"a":0,"k":100,"ix":11}},"ef":[],"w":500,"h":500,"refId":"comp_0","ind":1},{"ty":0,"nm":"Main","sr":1,"st":33,"op":66,"ip":34,"hd":false,"ddd":0,"bm":0,"hasMask":false,"ao":0,"ks":{"a":{"a":0,"k":[250,250,0],"ix":1},"s":{"a":0,"k":[100,100,100],"ix":6},"sk":{"a":0,"k":0},"p":{"a":0,"k":[250,250,0],"ix":2},"r":{"a":0,"k":0,"ix":10},"sa":{"a":0,"k":0},"o":{"a":0,"k":100,"ix":11}},"ef":[],"w":500,"h":500,"refId":"comp_1","ind":2}],"v":"5.6.6","fr":25,"op":65,"ip":0,"assets":[{"nm":"","id":"comp_0","layers":[{"ty":4,"nm":"Кривые bluetooth-svgrepo-com","sr":1,"st":0,"op":34,"ip":0,"hd":false,"ddd":0,"bm":0,"hasMask":false,"ao":0,"ks":{"a":{"a":0,"k":[112,112,0],"ix":1},"s":{"a":1,"k":[{"o":{"x":0.333,"y":0},"i":{"x":0.667,"y":1},"s":[100,100,100],"t":0},{"o":{"x":0.333,"y":0},"i":{"x":0.667,"y":1},"s":[115,115,100],"t":8.333},{"o":{"x":0.333,"y":0},"i":{"x":0.667,"y":1},"s":[95,95,100],"t":16.667},{"o":{"x":0.333,"y":0},"i":{"x":0.667,"y":1},"s":[100,100,100],"t":25},{"s":[0,0,100],"t":34}],"ix":6},"sk":{"a":0,"k":0},"p":{"a":0,"k":[260,256,0],"ix":2},"r":{"a":1,"k":[{"o":{"x":0.333,"y":0},"i":{"x":0.667,"y":1},"s":[0],"t":25},{"s":[180],"t":44}],"ix":10},"sa":{"a":0,"k":0},"o":{"a":0,"k":100,"ix":11}},"ef":[],"shapes":[{"ty":"gr","bm":0,"hd":false,"mn":"ADBE Vector Group","nm":"Группа 1","ix":1,"cix":2,"np":6,"it":[{"ty":"sh","bm":0,"hd":false,"mn":"ADBE Vector Shape - Group","nm":"Контур 1","ix":1,"d":1,"ks":{"a":0,"k":{"c":true,"i":[[0,0],[0,0],[0,0]],"o":[[0,0],[0,0],[0,0]],"v":[[17.999,64.267],[17.999,33.867],[33.199,49.067]]},"ix":2}},{"ty":"sh","bm":0,"hd":false,"mn":"ADBE Vector Shape - Group","nm":"Контур 2","ix":2,"d":1,"ks":{"a":0,"k":{"c":true,"i":[[0,0],[0,0],[0,0]],"o":[[0,0],[0,0],[0,0]],"v":[[17.999,-64.233],[33.199,-49.033],[17.999,-33.833]]},"ix":2}},{"ty":"sh","bm":0,"hd":false,"mn":"ADBE Vector Shape - Group","nm":"Контур 3","ix":3,"d":1,"ks":{"a":0,"k":{"c":true,"i":[[5.801,5.2],[0,0],[0,0],[5.801,5.7],[0,0],[3.701,0],[0,-7.9],[0,0],[0,0],[-13.599,-13.1],[0,0],[0,0],[-13.1,14.199],[0,0],[0,0],[-8.901,8.899],[0,0]],"o":[[0,0],[0,0],[5.801,-5.8],[0,0],[-2.601,-2.6],[-7.799,0],[0,0],[0,0],[-13.1,-13.6],[0,0],[0,0],[-13.599,13.099],[0,0],[0,0],[0,12.6],[0,0],[5.801,-5.2]],"v":[[62.499,39.067],[23.8,-0.233],[62.499,-39.033],[62.499,-58.933],[13.8,-107.733],[3.899,-111.933],[-9.701,-97.733],[-9.701,-33.733],[-34.8,-58.933],[-54.701,-39.033],[-15.501,-0.233],[-54.701,39.067],[-34.8,58.467],[-9.701,33.767],[-9.701,97.767],[13.8,107.767],[62.499,58.467]]},"ix":2}},{"ty":"mm","bm":0,"hd":false,"mn":"ADBE Vector Filter - Merge","nm":"Объединить контуры 1","mm":1},{"ty":"mm","bm":0,"hd":false,"mn":"ADBE Vector Filter - Merge","nm":"Объединить контуры 2","mm":4},{"ty":"fl","bm":0,"hd":false,"mn":"ADBE Vector Graphic - Fill","nm":"Заливка 1","c":{"a":0,"k":[1,1,1],"ix":4},"r":1,"o":{"a":0,"k":100,"ix":5}},{"ty":"tr","a":{"a":0,"k":[0,0],"ix":1},"s":{"a":0,"k":[100,100],"ix":3},"sk":{"a":0,"k":0,"ix":4},"p":{"a":0,"k":[108.104,111.934],"ix":2},"r":{"a":0,"k":0,"ix":6},"sa":{"a":0,"k":0,"ix":5},"o":{"a":0,"k":100,"ix":7}}]}],"ind":1},{"ty":4,"nm":"Слой-фигура 1","sr":1,"st":0,"op":35,"ip":0,"hd":false,"ddd":0,"bm":0,"hasMask":false,"ao":0,"ks":{"a":{"a":0,"k":[12,2,0],"ix":1},"s":{"a":1,"k":[{"o":{"x":0.333,"y":0},"i":{"x":0.667,"y":1},"s":[100,100,100],"t":25},{"s":[0,0,100],"t":35}],"ix":6},"sk":{"a":0,"k":0},"p":{"a":0,"k":[262,252,0],"ix":2},"r":{"a":0,"k":0,"ix":10},"sa":{"a":0,"k":0},"o":{"a":0,"k":100,"ix":11}},"ef":[],"shapes":[{"ty":"gr","bm":0,"hd":false,"mn":"ADBE Vector Group","nm":"Эллипс 1","ix":1,"cix":2,"np":3,"it":[{"ty":"el","bm":0,"hd":false,"mn":"ADBE Vector Shape - Ellipse","nm":"Контур эллипса 1","d":1,"p":{"a":0,"k":[0,0],"ix":3},"s":{"a":1,"k":[{"o":{"x":0.333,"y":0},"i":{"x":0.667,"y":1},"s":[300,300],"t":0},{"o":{"x":0.333,"y":0},"i":{"x":0.667,"y":1},"s":[280,280],"t":8.333},{"o":{"x":0.333,"y":0},"i":{"x":0.667,"y":1},"s":[320,320],"t":16.667},{"s":[300,300],"t":25}],"ix":2}},{"ty":"st","bm":0,"hd":false,"mn":"ADBE Vector Graphic - Stroke","nm":"Обводка 1","lc":1,"lj":1,"ml":4,"o":{"a":0,"k":100,"ix":4},"w":{"a":0,"k":0,"ix":5},"c":{"a":0,"k":[1,1,1],"ix":3}},{"ty":"fl","bm":0,"hd":false,"mn":"ADBE Vector Graphic - Fill","nm":"Заливка 1","c":{"a":0,"k":[0,0.6196,0.8902],"ix":4},"r":1,"o":{"a":0,"k":100,"ix":5}},{"ty":"tr","a":{"a":0,"k":[0,0],"ix":1},"s":{"a":0,"k":[100,100],"ix":3},"sk":{"a":0,"k":0,"ix":4},"p":{"a":0,"k":[12,2],"ix":2},"r":{"a":0,"k":0,"ix":6},"sa":{"a":0,"k":0,"ix":5},"o":{"a":0,"k":100,"ix":7}}]}],"ind":2},{"ty":4,"nm":"Слой-фигура 2","sr":1,"st":0,"op":25,"ip":0,"hd":false,"ddd":0,"bm":0,"hasMask":false,"ao":0,"ks":{"a":{"a":0,"k":[0,0,0],"ix":1},"s":{"a":0,"k":[100,100,100],"ix":6},"sk":{"a":0,"k":0},"p":{"a":0,"k":[250,250,0],"ix":2},"r":{"a":0,"k":0,"ix":10},"sa":{"a":0,"k":0},"o":{"a":0,"k":100,"ix":11}},"ef":[],"shapes":[{"ty":"gr","bm":0,"hd":false,"mn":"ADBE Vector Group","nm":"Эллипс 1","ix":1,"cix":2,"np":3,"it":[{"ty":"el","bm":0,"hd":false,"mn":"ADBE Vector Shape - Ellipse","nm":"Контур эллипса 1","d":1,"p":{"a":0,"k":[0,0],"ix":3},"s":{"a":0,"k":[300,300],"ix":2}},{"ty":"st","bm":0,"hd":false,"mn":"ADBE Vector Graphic - Stroke","nm":"Обводка 1","lc":1,"lj":1,"ml":4,"o":{"a":0,"k":100,"ix":4},"w":{"a":0,"k":0,"ix":5},"c":{"a":0,"k":[1,1,1],"ix":3}},{"ty":"fl","bm":0,"hd":false,"mn":"ADBE Vector Graphic - Fill","nm":"Заливка 1","c":{"a":0,"k":[0,0.6196,0.8902],"ix":4},"r":1,"o":{"a":0,"k":100,"ix":5}},{"ty":"tr","a":{"a":0,"k":[0,0],"ix":1},"s":{"a":0,"k":[100,100],"ix":3},"sk":{"a":0,"k":0,"ix":4},"p":{"a":0,"k":[12,2],"ix":2},"r":{"a":0,"k":0,"ix":6},"sa":{"a":0,"k":0,"ix":5},"o":{"a":0,"k":100,"ix":7}}]}],"ind":3},{"ty":4,"nm":"Слой-фигура 3","sr":1,"st":0,"op":25,"ip":0,"hd":false,"ddd":0,"bm":0,"hasMask":false,"ao":0,"ks":{"a":{"a":0,"k":[0,0,0],"ix":1},"s":{"a":1,"k":[{"o":{"x":0.333,"y":0},"i":{"x":0.667,"y":1},"s":[100,100,100],"t":0},{"o":{"x":0.333,"y":0},"i":{"x":0.667,"y":1},"s":[120,120,100],"t":8.333},{"o":{"x":0.333,"y":0},"i":{"x":0.667,"y":1},"s":[110,110,100],"t":16.667},{"s":[100,100,100],"t":25}],"ix":6},"sk":{"a":0,"k":0},"p":{"a":0,"k":[250,250,0],"ix":2},"r":{"a":0,"k":0,"ix":10},"sa":{"a":0,"k":0},"o":{"a":0,"k":100,"ix":11}},"ef":[],"shapes":[{"ty":"gr","bm":0,"hd":false,"mn":"ADBE Vector Group","nm":"Эллипс 1","ix":1,"cix":2,"np":3,"it":[{"ty":"el","bm":0,"hd":false,"mn":"ADBE Vector Shape - Ellipse","nm":"Контур эллипса 1","d":1,"p":{"a":0,"k":[0,0],"ix":3},"s":{"a":0,"k":[300,300],"ix":2}},{"ty":"st","bm":0,"hd":false,"mn":"ADBE Vector Graphic - Stroke","nm":"Обводка 1","lc":1,"lj":1,"ml":4,"o":{"a":0,"k":100,"ix":4},"w":{"a":0,"k":0,"ix":5},"c":{"a":0,"k":[1,1,1],"ix":3}},{"ty":"fl","bm":0,"hd":false,"mn":"ADBE Vector Graphic - Fill","nm":"Заливка 1","c":{"a":0,"k":[0,0.6196,0.8902],"ix":4},"r":1,"o":{"a":0,"k":100,"ix":5}},{"ty":"tr","a":{"a":0,"k":[0,0],"ix":1},"s":{"a":0,"k":[100,100],"ix":3},"sk":{"a":0,"k":0,"ix":4},"p":{"a":0,"k":[12,2],"ix":2},"r":{"a":0,"k":0,"ix":6},"sa":{"a":0,"k":0,"ix":5},"o":{"a":0,"k":100,"ix":7}}]}],"ind":4}]},{"nm":"","id":"comp_1","layers":[{"ty":0,"nm":"Check","sr":1,"st":7,"op":47,"ip":7,"hd":false,"ddd":0,"bm":0,"hasMask":false,"ao":0,"ks":{"a":{"a":0,"k":[217.62,172.689,0],"ix":1},"s":{"a":1,"k":[{"o":{"x":0.333,"y":0},"i":{"x":0.667,"y":1},"s":[100,100,100],"t":17},{"o":{"x":0.333,"y":0},"i":{"x":0.667,"y":1},"s":[90,90,100],"t":21},{"s":[100,100,100],"t":27}],"ix":6},"sk":{"a":0,"k":0},"p":{"a":1,"k":[{"o":{"x":0.333,"y":0},"i":{"x":0.667,"y":1},"s":[212,164,0],"t":17,"ti":[0,0,0],"to":[1.667,1.333,0]},{"o":{"x":0.333,"y":0},"i":{"x":0.667,"y":1},"s":[222,172,0],"t":21,"ti":[1.667,1.333,0],"to":[0,0,0]},{"s":[212,164,0],"t":27}],"ix":2},"r":{"a":1,"k":[{"o":{"x":0.333,"y":0},"i":{"x":0.667,"y":1},"s":[-39],"t":7},{"s":[0],"t":17}],"ix":10},"sa":{"a":0,"k":0},"o":{"a":0,"k":100,"ix":11}},"ef":[],"w":500,"h":500,"refId":"comp_2","ind":1},{"ty":4,"nm":"Circle","sr":1,"st":0,"op":45,"ip":0,"hd":false,"ddd":0,"bm":0,"hasMask":false,"ao":0,"ks":{"a":{"a":0,"k":[0,0,0],"ix":1},"s":{"a":0,"k":[100,100,100],"ix":6},"sk":{"a":0,"k":0},"p":{"a":0,"k":[250,250,0],"ix":2},"r":{"a":0,"k":0,"ix":10},"sa":{"a":0,"k":0},"o":{"a":0,"k":100,"ix":11}},"ef":[],"shapes":[{"ty":"gr","bm":0,"hd":false,"mn":"ADBE Vector Group","nm":"Эллипс 1","ix":1,"cix":2,"np":3,"it":[{"ty":"el","bm":0,"hd":false,"mn":"ADBE Vector Shape - Ellipse","nm":"Контур эллипса 1","d":1,"p":{"a":0,"k":[0,0],"ix":3},"s":{"a":1,"k":[{"o":{"x":0.333,"y":0},"i":{"x":0.667,"y":1},"s":[0,0],"t":0},{"o":{"x":0.333,"y":0},"i":{"x":0.667,"y":1},"s":[460,460],"t":9.842},{"o":{"x":0.167,"y":0},"i":{"x":0.833,"y":1},"s":[300,300],"t":16},{"s":[450,450],"t":26}],"ix":2}},{"ty":"fl","bm":0,"hd":false,"mn":"ADBE Vector Graphic - Fill","nm":"Заливка 1","c":{"a":0,"k":[0.3373,0.3961,0],"ix":4},"r":1,"o":{"a":1,"k":[{"o":{"x":0.333,"y":0},"i":{"x":0.667,"y":1},"s":[25],"t":0},{"s":[100],"t":6.7060546875}],"ix":5}},{"ty":"tr","a":{"a":0,"k":[0,0],"ix":1},"s":{"a":0,"k":[100,100],"ix":3},"sk":{"a":0,"k":0,"ix":4},"p":{"a":0,"k":[0,0],"ix":2},"r":{"a":0,"k":0,"ix":6},"sa":{"a":0,"k":0,"ix":5},"o":{"a":0,"k":100,"ix":7}}]}],"ind":2},{"ty":4,"nm":"Circle 2","sr":1,"st":0,"op":45,"ip":0,"hd":false,"ddd":0,"bm":0,"hasMask":false,"ao":0,"ks":{"a":{"a":0,"k":[0,0,0],"ix":1},"s":{"a":0,"k":[100,100,100],"ix":6},"sk":{"a":0,"k":0},"p":{"a":0,"k":[250,250,0],"ix":2},"r":{"a":0,"k":0,"ix":10},"sa":{"a":0,"k":0},"o":{"a":0,"k":100,"ix":11}},"ef":[],"shapes":[{"ty":"gr","bm":0,"hd":false,"mn":"ADBE Vector Group","nm":"Эллипс 1","ix":1,"cix":2,"np":3,"it":[{"ty":"el","bm":0,"hd":false,"mn":"ADBE Vector Shape - Ellipse","nm":"Контур эллипса 1","d":1,"p":{"a":0,"k":[0,0],"ix":3},"s":{"a":1,"k":[{"o":{"x":0.333,"y":0},"i":{"x":0.667,"y":1},"s":[0,0],"t":0},{"o":{"x":0.297,"y":0},"i":{"x":0.66,"y":0.963},"s":[460,460],"t":9.842},{"o":{"x":0.425,"y":-0.054},"i":{"x":0.814,"y":1},"s":[400,400],"t":16},{"s":[450,450],"t":22}],"ix":2}},{"ty":"fl","bm":0,"hd":false,"mn":"ADBE Vector Graphic - Fill","nm":"Заливка 1","c":{"a":0,"k":[0.3373,0.3961,0],"ix":4},"r":1,"o":{"a":1,"k":[{"o":{"x":0.333,"y":0},"i":{"x":0.667,"y":1},"s":[25],"t":0},{"s":[100],"t":6.7060546875}],"ix":5}},{"ty":"tr","a":{"a":0,"k":[0,0],"ix":1},"s":{"a":0,"k":[100,100],"ix":3},"sk":{"a":0,"k":0,"ix":4},"p":{"a":0,"k":[0,0],"ix":2},"r":{"a":0,"k":0,"ix":6},"sa":{"a":0,"k":0,"ix":5},"o":{"a":0,"k":100,"ix":7}}]}],"ind":3}]},{"nm":"","id":"comp_2","layers":[{"ty":4,"nm":"Слой-фигура 5","sr":1,"st":0,"op":50,"ip":4,"hd":false,"ddd":0,"bm":0,"hasMask":false,"ao":0,"ks":{"a":{"a":0,"k":[0,0,0],"ix":1},"s":{"a":0,"k":[100,100,100],"ix":6},"sk":{"a":0,"k":0},"p":{"a":0,"k":[422,273.5,0],"ix":2},"r":{"a":0,"k":0,"ix":10},"sa":{"a":0,"k":0},"o":{"a":0,"k":100,"ix":11}},"ef":[],"shapes":[{"ty":"gr","bm":0,"hd":false,"mn":"ADBE Vector Group","nm":"Фигура 1","ix":1,"cix":2,"np":3,"it":[{"ty":"sh","bm":0,"hd":false,"mn":"ADBE Vector Shape - Group","nm":"Контур 1","ix":1,"d":1,"ks":{"a":1,"k":[{"o":{"x":0.333,"y":0},"i":{"x":0.667,"y":1},"s":[{"c":false,"i":[[0,0],[0,0]],"o":[[0,0],[0,0]],"v":[[-162,35.5],[-182,58]]}],"t":5},{"s":[{"c":false,"i":[[0,0],[0,0]],"o":[[0,0],[0,0]],"v":[[-78,-71],[-182,58]]}],"t":11}],"ix":2}},{"ty":"st","bm":0,"hd":false,"mn":"ADBE Vector Graphic - Stroke","nm":"Обводка 1","lc":2,"lj":3,"ml":1,"o":{"a":0,"k":100,"ix":4},"w":{"a":0,"k":50,"ix":5},"c":{"a":0,"k":[1,1,1],"ix":3}},{"ty":"fl","bm":0,"hd":false,"mn":"ADBE Vector Graphic - Fill","nm":"Заливка 1","c":{"a":0,"k":[1,1,1],"ix":4},"r":1,"o":{"a":0,"k":100,"ix":5}},{"ty":"tr","a":{"a":0,"k":[0,0],"ix":1},"s":{"a":0,"k":[100,100],"ix":3},"sk":{"a":0,"k":0,"ix":4},"p":{"a":0,"k":[0,0],"ix":2},"r":{"a":0,"k":0,"ix":6},"sa":{"a":0,"k":0,"ix":5},"o":{"a":0,"k":100,"ix":7}}]}],"ind":1},{"ty":4,"nm":"Слой-фигура 4","sr":1,"st":0,"op":50,"ip":-1,"hd":false,"ddd":0,"bm":0,"hasMask":false,"ao":0,"ks":{"a":{"a":0,"k":[0,0,0],"ix":1},"s":{"a":0,"k":[100,100,100],"ix":6},"sk":{"a":0,"k":0},"p":{"a":0,"k":[286,214,0],"ix":2},"r":{"a":0,"k":0,"ix":10},"sa":{"a":0,"k":0},"o":{"a":0,"k":100,"ix":11}},"ef":[],"shapes":[{"ty":"gr","bm":0,"hd":false,"mn":"ADBE Vector Group","nm":"Фигура 1","ix":1,"cix":2,"np":3,"it":[{"ty":"sh","bm":0,"hd":false,"mn":"ADBE Vector Shape - Group","nm":"Контур 1","ix":1,"d":1,"ks":{"a":1,"k":[{"o":{"x":0.167,"y":0.167},"i":{"x":0.833,"y":0.833},"s":[{"c":false,"i":[[0,0],[0,0]],"o":[[0,0],[0,0]],"v":[[-119,65.5],[-119,66]]}],"t":0},{"s":[{"c":false,"i":[[0,0],[0,0]],"o":[[0,0],[0,0]],"v":[[-119,65.5],[-48,118.25]]}],"t":4}],"ix":2}},{"ty":"st","bm":0,"hd":false,"mn":"ADBE Vector Graphic - Stroke","nm":"Обводка 1","lc":2,"lj":1,"ml":4,"o":{"a":0,"k":100,"ix":4},"w":{"a":0,"k":50,"ix":5},"c":{"a":0,"k":[1,1,1],"ix":3}},{"ty":"fl","bm":0,"hd":false,"mn":"ADBE Vector Graphic - Fill","nm":"Заливка 1","c":{"a":0,"k":[1,1,1],"ix":4},"r":1,"o":{"a":0,"k":100,"ix":5}},{"ty":"tr","a":{"a":0,"k":[0,0],"ix":1},"s":{"a":0,"k":[100,100],"ix":3},"sk":{"a":0,"k":0,"ix":4},"p":{"a":0,"k":[0,0],"ix":2},"r":{"a":0,"k":0,"ix":6},"sa":{"a":0,"k":0,"ix":5},"o":{"a":0,"k":100,"ix":7}}]}],"ind":2}]}]}